# 一般 python 开发者都不用的冷特性——Optimize

> :fontawesome-regular-face-grin: 唐彬
>
> :material-clock-edit-outline: 2023年6月22日 0:06:53

assert 语句其实在运行时可选。指定`-O`参数或`$PYTHONOPTIMIZE`环境变量时，会移除所有`assert`和`if __debug__`。

```python title="lie.py"
print("Vulcans are incapable of lying.")

if __debug__:
    print("They just *exaggerate*.")

assert not "a lie"
```

`python lie.py`（Windows 上请`py lie.py`）结果如下。

```
Vulcans are incapable of lying.
They just *exaggerate*.
Traceback (most recent call last):
    File "lie.py", line 6, in <module>
    assert not "a lie"
AssertionError
```

而`python -O lie.py`结果只有`Vulcans are incapable of lying.`。

注意这种删除是直接把语句删了，而不是运行时再判断。你可以用 dis 模块在字节码层面验证这一点。

```shell
$ py -O -m dis lie.py
  0           0 RESUME                   0

  1           2 PUSH_NULL
              4 LOAD_NAME                0 (print)
              6 LOAD_CONST               0 ('Vulcans are incapable of lying.')
              8 PRECALL                  1
             12 CALL                     1
             22 POP_TOP

  3          24 LOAD_CONST               3 (None)
             26 RETURN_VALUE
```

:material-eye-arrow-right-outline: [The best Python feature you cannot use - Bite code!](https://www.bitecode.dev/p/the-best-python-feature-you-cannot)

:material-eye-arrow-right-outline: [`$PYTHONOPTIMIZE` - Command line and environment — Python 3.11 documentation](https://docs.python.org/3.11/using/cmdline.html#envvar-PYTHONOPTIMIZE)

:material-eye-arrow-right-outline: [`-O` - Command line and environment — Python 3.11 documentation](https://docs.python.org/3.11/using/cmdline.html#cmdoption-O)

:material-eye-arrow-right-outline: [The assert statement - Simple statements — Python 3.11 documentation](https://docs.python.org/3.11/reference/simple_stmts.html#assert)

:material-eye-arrow-right-outline: [`__debug__` - Built-in Constants — Python 3.11 documentation](https://docs.python.org/3.11/library/constants.html#debug__)

:material-eye-arrow-right-outline: [dis — Disassembler for Python bytecode — Python 3.11.4 documentation](https://docs.python.org/3.11/library/dis.html)
